jupyterlab_notify/__init__.py
jupyterlab_notify/_version.py
jupyterlab_notify/magics.py
jupyterlab_notify-2.0.2.data/data/etc/jupyter/jupyter_notebook_config.d/jupyterlab_notify.json
jupyterlab_notify-2.0.2.data/data/etc/jupyter/jupyter_server_config.d/jupyterlab_notify.json
jupyterlab_notify-2.0.2.data/data/share/jupyter/labextensions/jupyterlab-notify/package.json
jupyterlab_notify-2.0.2.data/data/share/jupyter/labextensions/jupyterlab-notify/static/568.57c7601c094627c928c3.js
jupyterlab_notify-2.0.2.data/data/share/jupyter/labextensions/jupyterlab-notify/static/747.a8203475eacf622d6015.js
jupyterlab_notify-2.0.2.data/data/share/jupyter/labextensions/jupyterlab-notify/static/remoteEntry.2991307e8c084a1fcd65.js
jupyterlab_notify-2.0.2.data/data/share/jupyter/labextensions/jupyterlab-notify/static/style.js
jupyterlab_notify-2.0.2.data/data/share/jupyter/labextensions/jupyterlab-notify/static/third-party-licenses.json
jupyterlab_notify-2.0.2.data/data/share/jupyter/labextensions/jupyterlab-notify/install.json
jupyterlab_notify-2.0.2.dist-info/METADATA
jupyterlab_notify-2.0.2.dist-info/WHEEL
jupyterlab_notify-2.0.2.dist-info/licenses/LICENSE.txt
jupyterlab_notify-2.0.2.dist-info/RECORD
